ds4finance/__init__.py
ds4finance/functions.py
ds4finance-0.1.20.dist-info/LICENSE.txt
ds4finance-0.1.20.dist-info/METADATA
ds4finance-0.1.20.dist-info/WHEEL
ds4finance-0.1.20.dist-info/top_level.txt
ds4finance-0.1.20.dist-info/RECORD
